acond_heat_pump/__init__.py
acond_heat_pump/constants.py
acond_heat_pump/heat_pump.py
acond_heat_pump/heat_pump_data.py
acond_heat_pump-1.0.0.dist-info/LICENSE
acond_heat_pump-1.0.0.dist-info/METADATA
acond_heat_pump-1.0.0.dist-info/WHEEL
acond_heat_pump-1.0.0.dist-info/RECORD
