Metadata-Version: 2.1
Name: acond-heat-pump
Version: 1.0.0
Summary: A unofficial python library to interface with an Acond heat pump using the Modbus TCP protocol.
Author: Jiří Bireš
Requires-Python: >=3.12,<4.0
Classifier: Programming Language :: Python :: 3
Classifier: Programming Language :: Python :: 3.12
Classifier: Programming Language :: Python :: 3.13
Requires-Dist: pymodbus (>=3.7.4,<4.0.0)
